ivy_models/__init__.py
ivy_models/transformers/__init__.py
ivy_models/transformers/helpers.py
ivy_models/transformers/perceiver_io.py
ivy_models-1.1.9.dist-info/LICENSE
ivy_models-1.1.9.dist-info/METADATA
ivy_models-1.1.9.dist-info/WHEEL
ivy_models-1.1.9.dist-info/top_level.txt
ivy_models-1.1.9.dist-info/RECORD
